rocket_a/__init__.py
rocket_a/rocket.py
rocket_a-1.0.0.dist-info/LICENSE.txt
rocket_a-1.0.0.dist-info/METADATA
rocket_a-1.0.0.dist-info/WHEEL
rocket_a-1.0.0.dist-info/top_level.txt
rocket_a-1.0.0.dist-info/RECORD
