Metadata-Version: 2.1
Name: rocket_a
Version: 1.0.0
Summary: An awesome package that does something
Home-page: http://pypi.python.org/pypi/rocket_a/
Author: firdaws
Author-email: firdawsbenahmed20@gmail.com
License: LICENSE.txt
License-File: LICENSE.txt
Requires-Dist: rocket-a
